kiwano/__init__.py
kiwano/kiwano.py
kiwano-0.2.0.data/scripts/kiwano
kiwano-0.2.0.dist-info/METADATA
kiwano-0.2.0.dist-info/RECORD
kiwano-0.2.0.dist-info/WHEEL
kiwano-0.2.0.dist-info/top_level.txt
